BetterTurtle.py
BetterTurtle-0.0.3.dist-info/LICENSE
BetterTurtle-0.0.3.dist-info/METADATA
BetterTurtle-0.0.3.dist-info/WHEEL
BetterTurtle-0.0.3.dist-info/top_level.txt
BetterTurtle-0.0.3.dist-info/RECORD
