Metadata-Version: 2.1
Name: BetterTurtle
Version: 0.0.3
Summary: A better turtle module for python. Uses turtle module to create a turtle object with additional functionality.
License-File: LICENSE
